gbfs/__init__.py
gbfs/algorithms/__init__.py
gbfs/algorithms/base.py
gbfs/algorithms/gb_afs/__init__.py
gbfs/algorithms/gb_afs/gbafs.py
gbfs/algorithms/gb_bc_fs/__init__.py
gbfs/algorithms/gb_bc_fs/gbbcfs.py
gbfs/algorithms/gb_bc_fs/heuristic.py
gbfs/feature_selection/__init__.py
gbfs/feature_selection/clustering.py
gbfs/feature_selection/feature_space.py
gbfs/feature_selection/knee_locator.py
gbfs/feature_selection/mss.py
gbfs/models/data_view.py
gbfs/models/dim_reducer.py
gbfs/utils/__init__.py
gbfs/utils/data_processor.py
gbfs/utils/distance.py
gbfs-0.2.1.dist-info/LICENSE
gbfs-0.2.1.dist-info/METADATA
gbfs-0.2.1.dist-info/WHEEL
gbfs-0.2.1.dist-info/RECORD
