Metadata-Version: 2.1
Name: gbfs
Version: 0.2.1
Summary: Graph-Based Feature-Selection Algorithms
Home-page: https://github.com/davidlevinwork/gbfs/
License: MIT
Keywords: feature-selection,automatic-feature-selection,clustering,dimensionality-reduction
Author: David Levin
Author-email: davidlevin40@gmail.com
Requires-Python: >=3.10,<4.0
Classifier: Development Status :: 5 - Production/Stable
Classifier: Intended Audience :: Science/Research
Classifier: License :: OSI Approved :: MIT License
Classifier: Operating System :: OS Independent
Classifier: Programming Language :: Python :: 3
Classifier: Programming Language :: Python :: 3.10
Classifier: Programming Language :: Python :: 3.11
Classifier: Programming Language :: Python :: 3.12
Classifier: Programming Language :: Python :: 3 :: Only
Classifier: Topic :: Scientific/Engineering :: Artificial Intelligence
Requires-Dist: kneed (>=0.8.5,<0.9.0)
Requires-Dist: matplotlib (>=3.8.3,<4.0.0)
Requires-Dist: pandas (>=2.2.1,<3.0.0)
Requires-Dist: scikit-learn (>=1.4.1.post1,<2.0.0)
Requires-Dist: scikit-learn-extra (>=0.3.0,<0.4.0)
Requires-Dist: seaborn (>=0.13.2,<0.14.0)
Requires-Dist: tqdm (>=4.66.4,<5.0.0)
Project-URL: Documentation, https://davidlevinwork.github.io/gbfs/
Project-URL: Repository, https://github.com/davidlevinwork/gbfs/
